farmyard-0.0.1.dev3.dist-info/METADATA
farmyard-0.0.1.dev3.dist-info/WHEEL
farmyard-0.0.1.dev3.dist-info/license_files/LICENSE
farmyard/_native/_farmyard_native.py
farmyard/_native/__init__.py
farmyard/__init__.py
farmyard/_native/_farmyard_native.cp39-win_amd64.pyd
farmyard-0.0.1.dev3.dist-info/RECORD
