Metadata-Version: 2.1
Name: farmyard
Version: 0.0.1.dev3
Classifier: License :: OSI Approved :: MIT License
Classifier: Operating System :: OS Independent
Classifier: Programming Language :: Rust
Classifier: Programming Language :: Python :: Implementation :: CPython
Classifier: Programming Language :: Python :: Implementation :: PyPy
Classifier: Programming Language :: Python :: 3.8
Classifier: Programming Language :: Python :: 3.9
Classifier: Programming Language :: Python :: 3.10
Requires-Dist: pip>=21
Requires-Dist: numpy~=1.20
Requires-Dist: pytest>=6.2.4; extra == 'test'
Requires-Dist: pytest-cov>=2.12.1; extra == 'test'
Provides-Extra: test
License-File: LICENSE
Summary: The Minimal Reinforcement Learning Framework
Author: Nathan Michlo <nathanjmichlo@gmail.com>
Author-email: Nathan Juraj Michlo <NathanJMichlo@gmail.com>
Requires-Python: >=3.8
Project-URL: homepage, https://github.com/nmichlo/farmyard
Project-URL: repository, https://github.com/nmichlo/farmyard
